holotol_framework/__init__.py
holotol_framework/data_loader.py
holotol_framework/data_processor.py
holotol_framework/framework.py
holotol_framework/pipeline.py
holotol_framework-0.1.5.dist-info/METADATA
holotol_framework-0.1.5.dist-info/WHEEL
holotol_framework-0.1.5.dist-info/licenses/LICENSE
holotol_framework-0.1.5.dist-info/RECORD
