Metadata-Version: 2.4
Name: holotol-framework
Version: 0.1.5
Summary: A Python package for integrating biological sequence data with a conceptual HoloToL framework.
Project-URL: Homepage, https://github.com/kambrosgroup/HoloTol
Project-URL: Bug Tracker, https://github.com/kambrosgroup/HoloTol/issues
Author-email: Karl Ambrosius <karlambrosius@outlook.com.au>
License: MIT
License-File: LICENSE
Keywords: bioinformatics,biology,evolution,ncbi,quantum
Classifier: Intended Audience :: Science/Research
Classifier: License :: OSI Approved :: MIT License
Classifier: Operating System :: OS Independent
Classifier: Programming Language :: Python :: 3
Classifier: Topic :: Scientific/Engineering :: Bio-Informatics
Requires-Python: >=3.8
Requires-Dist: biopython
Requires-Dist: numpy
Requires-Dist: pandas
Requires-Dist: scikit-learn
Requires-Dist: scipy
